esovalue/__init__.py
esovalue/eso.py
esovalue/trinomial_tree.py
esovalue-0.1.13.dist-info/LICENSE
esovalue-0.1.13.dist-info/WHEEL
esovalue-0.1.13.dist-info/METADATA
esovalue-0.1.13.dist-info/RECORD
