Metadata-Version: 2.1
Name: esovalue
Version: 0.1.13
Summary: Valuation of employee stock options
Home-page: https://github.com/snthibaud/esovalue
License: MIT
Author: Stéphane Thibaud
Author-email: snthibaud@gmail.com
Requires-Python: >=3.9,<3.11
Classifier: License :: OSI Approved :: MIT License
Classifier: Programming Language :: Python :: 3
Classifier: Programming Language :: Python :: 3.10
Classifier: Programming Language :: Python :: 3.9
Requires-Dist: Pillow (>=9.1.1)
Requires-Dist: gmpy
Requires-Dist: mistune (>=2.0.3)
Requires-Dist: mpmath
Project-URL: ESO valuation app, https://eso.stephanethibaud.xyz/
Project-URL: Repository, https://github.com/snthibaud/esovalue
